COPYING
MANIFEST.in
README
setup.py
version
./__init__.py
./fhir.py
./fhir_test.py
doc/CREDITS
doc/index.rst
fhir.egg-info/PKG-INFO
fhir.egg-info/SOURCES.txt
fhir.egg-info/dependency_links.txt
fhir.egg-info/top_level.txt
locale/es_ES.po
locale/fr_FR.po
locale/it_IT.po