Metadata-Version: 1.1
Name: fhir
Version: 0.0.4
Summary: HL7 FHIR Library
Home-page: http://health.gnu.org
Author: Luis Falcon
Author-email: lfalcon@gnusolidario.org
License: GPL-3
Download-URL: http://ftp.gnu.org/gnu/health/
Keywords: HL7 FHIR GNUHEALTH
Platform: UNKNOWN
Classifier: Development Status :: 3 - Alpha
Classifier: Environment :: Plugins
Classifier: Intended Audience :: Developers
Classifier: Intended Audience :: Healthcare Industry
Classifier: License :: OSI Approved :: GNU General Public License (GPL)
Classifier: Natural Language :: English
Classifier: Natural Language :: Spanish
Classifier: Operating System :: OS Independent
Classifier: Programming Language :: Python :: 2.6
Classifier: Programming Language :: Python :: 2.7
Classifier: Topic :: Scientific/Engineering :: Bio-Informatics
Classifier: Topic :: Scientific/Engineering :: Medical Science Apps.
Requires: requests
